Workbook

Sheet Start Here
A1: WELCOME TO YOUR LONG-DISTANCE MOVE TRACKER
A2: A calm, practical workbook to help you coordinate tasks, providers, costs, and changes during a long-distance move.
A4: YOUR WORKFLOW | Dashboard → Task Tracker → Providers → Budget → Contingencies
A5: HOW TO GET STARTED
A6: 1 | Start on Dashboard | C6: Enter your origin, destination, and planned move dates. The summary updates as you work in the other tabs.
A7: 2 | Customize Task Tracker | C7: Edit the sample tasks or add your own. Enter due dates, status, estimated costs, and notes about dependencies.
A8: 3 | Use the color alerts | C8: Red means an unfinished task is overdue; amber means it is due within 7 days; green means completed.
A9: 4 | Compare Providers | C9: Record written quotes, deposits, balances, service dates, pickup/delivery windows, and cancellation terms.
A10: 5 | Track the Budget | C10: Estimated costs for key providers pull from their quotes on Providers. Enter actual/final costs in Budget and mark expenses as paid when appropriate.
A11: 6 | Record changes | C11: Use Contingencies when plans change. Note what happened, what it affects, the next action, and who is responsible.
A13: IMPORTANT TO KNOW
A14: This workbook updates from information you enter. It does not connect to moving companies, verify quotes, or automatically detect appointment changes. Confirm dates, terms, and deadlines directly with each provider.
A17: HELPFUL TIP
A18: Some cells have dropdown menus with predefined choices, such as task status or provider type. Click a cell to see whether a dropdown is available, and select an option when appropriate. Use real dates in date fields, keep a backup copy as you customize the workbook, and check that automatic calculation is enabled if formulas do not update as expected.

Sheet Dashboard
A1: LONG-DISTANCE MOVE | DASHBOARD
A2: Your move at a glance. Update the other tabs and this overview will recalculate.
A4: MOVE DETAILS | D4: AT A GLANCE
A5: Origin | B5: Enter city / state | D5: Total estimated budget | E5: =Budget!C18 -> 0
A6: Destination | B6: Enter city / state | D6: Total actual costs | E6: =Budget!D18 -> 0
A7: Move-out date | D7: Tasks not complete | E7: =COUNTIF('Task Tracker'!D5:D54,"<>Complete")-COUNTBLANK('Task Tracker'!A5:A54) -> 10
A8: Move-in date | D8: Overdue tasks | E8: =COUNTIFS('Task Tracker'!D5:D54,"<>Complete",'Task Tracker'!C5:C54,"<"&TODAY(),'Task Tracker'!C5:C54,">0",'Task Tracker'!A5:A54,"<>") -> 0
D9: Completed tasks | E9: =COUNTIF('Task Tracker'!D5:D54,"Complete") -> 0
D10: Open contingency items | E10: =COUNTIFS(Contingencies!G5:G24,"<>Yes",Contingencies!A5:A24,"<>") -> 0
A11: HOW TO USE THIS DASHBOARD
A12: 1. Enter your origin, destination, and dates above. 2. Update tasks on Task Tracker. 3. Enter estimates and actual costs in Budget. 4. Record provider quotes and unexpected changes on their tabs.
A15: COLOR KEY
A16: OVERDUE — unfinished task past due
A17: COMING UP — due within 7 days
A18: COMPLETE — task finished

Sheet Task Tracker
A1: TASK TRACKER
A2: Sample tasks are examples only. Edit or delete them to fit your move; all sample tasks start as Not started.
A4: Task | B4: Category | C4: Due Date | D4: Status | E4: Estimated Cost ($) | F4: Depends On / Notes | G4: Days Until Due
A5: EXAMPLE: Compare quotes | B5: Booking | D5: Not started | F5: Example: Request written estimates from providers | G5: =IF(C5="","",C5-TODAY())
A6: EXAMPLE: Confirm delivery | B6: Shipment | D6: Not started | F6: Example: Confirm delivery window with provider | G6: =IF(C6="","",C6-TODAY())
A7: EXAMPLE: Finish loading container | B7: Loading | D7: Not started | F7: Example: Allow enough time for loading | G7: =IF(C7="","",C7-TODAY())
A8: EXAMPLE: Confirm pickup | B8: Shipment | D8: Not started | F8: Example: Confirm pickup timing with provider | G8: =IF(C8="","",C8-TODAY())
A9: EXAMPLE: Book unloading crew | B9: Destination | D9: Not started | F9: Example: Confirm expected delivery window first | G9: =IF(C9="","",C9-TODAY())
A10: EXAMPLE: Arrange vehicle transport | B10: Vehicle | D10: Not started | F10: Example: Record pickup and delivery windows | G10: =IF(C10="","",C10-TODAY())
A11: EXAMPLE: Set up destination utilities | B11: Utilities | D11: Not started | F11: Example: Check activation dates and access | G11: =IF(C11="","",C11-TODAY())
A12: EXAMPLE: Prepare essentials bag | B12: Travel | D12: Not started | F12: Example: Keep essentials accessible during travel | G12: =IF(C12="","",C12-TODAY())
A13: EXAMPLE: Inspect delivered belongings | B13: Delivery | D13: Not started | F13: Example: Photograph damage and record missing items | G13: =IF(C13="","",C13-TODAY())
A14: EXAMPLE: Update address and records | B14: Admin | D14: Not started | F14: Example: Check which agencies and providers need updates | G14: =IF(C14="","",C14-TODAY())
G15: =IF(C15="","",C15-TODAY())
G16: =IF(C16="","",C16-TODAY())
G17: =IF(C17="","",C17-TODAY())
G18: =IF(C18="","",C18-TODAY())
G19: =IF(C19="","",C19-TODAY())
G20: =IF(C20="","",C20-TODAY())
G21: =IF(C21="","",C21-TODAY())
G22: =IF(C22="","",C22-TODAY())
G23: =IF(C23="","",C23-TODAY())
G24: =IF(C24="","",C24-TODAY())
G25: =IF(C25="","",C25-TODAY())
G26: =IF(C26="","",C26-TODAY())
... G54: =IF(C54="","",C54-TODAY())

Sheet Providers
A1: PROVIDER COMPARISON
A2: Compare providers using written quotes and confirmed terms. To add another provider, use a blank row below and choose its Service Type from the dropdown.
A4: Service Type | B4: Company | C4: Contact / Phone | D4: Quote ($) | E4: Deposit ($) | F4: Balance ($) | G4: Pickup / Service Date | H4: Delivery Window / Notes | I4: Cancellation / Coverage Notes
A5: Moving company | F5: =IF(D5="","",IFERROR(D5-IF(E5="",0,E5),""))
A6: Container / POD service | F6: =IF(D6="","",IFERROR(D6-IF(E6="",0,E6),""))
A7: Self-storage facility | F7: =IF(D7="","",IFERROR(D7-IF(E7="",0,E7),""))
A8: Destination unloading crew | F8: =IF(D8="","",IFERROR(D8-IF(E8="",0,E8),""))
A9: Vehicle transport | F9: =IF(D9="","",IFERROR(D9-IF(E9="",0,E9),""))
F10: =IF(D10="","",IFERROR(D10-IF(E10="",0,E10),""))
F11: =IF(D11="","",IFERROR(D11-IF(E11="",0,E11),""))
F12: =IF(D12="","",IFERROR(D12-IF(E12="",0,E12),""))
F13: =IF(D13="","",IFERROR(D13-IF(E13="",0,E13),""))
F14: =IF(D14="","",IFERROR(D14-IF(E14="",0,E14),""))
F15: =IF(D15="","",IFERROR(D15-IF(E15="",0,E15),""))
F16: =IF(D16="","",IFERROR(D16-IF(E16="",0,E16),""))
F17: =IF(D17="","",IFERROR(D17-IF(E17="",0,E17),""))
F18: =IF(D18="","",IFERROR(D18-IF(E18="",0,E18),""))
F19: =IF(D19="","",IFERROR(D19-IF(E19="",0,E19),""))
F20: =IF(D20="","",IFERROR(D20-IF(E20="",0,E20),""))
F21: =IF(D21="","",IFERROR(D21-IF(E21="",0,E21),""))
... F24: =IF(D24="","",IFERROR(D24-IF(E24="",0,E24),""))

Sheet Budget
A1: MOVING BUDGET
A2: Estimated costs for the moving company, container, self-storage, unloading crew, and vehicle transport pull from Providers when a quote is entered. Enter final/updated costs in Actual ($). Positive variance means actual cost is over estimate.
A4: Expense | B4: Provider / Notes | C4: Estimated ($) (auto from Providers) | D4: Actual ($) (enter here) | E4: Variance ($) | F4: Paid?
A5: Moving company | C5: =IF(Providers!D5="","",Providers!D5) | E5: =IF(AND(C5="",D5=""),"",D5-C5) | F5: No
A6: Container / POD service | C6: =IF(Providers!D6="","",Providers!D6) | E6: =IF(AND(C6="",D6=""),"",D6-C6) | F6: No
A7: Self-storage facility | C7: =IF(Providers!D7="","",Providers!D7) | E7: =IF(AND(C7="",D7=""),"",D7-C7) | F7: No
A8: Destination unloading | C8: =IF(Providers!D8="","",Providers!D8) | E8: =IF(AND(C8="",D8=""),"",D8-C8) | F8: No
A9: Vehicle transport | C9: =IF(Providers!D9="","",Providers!D9) | E9: =IF(AND(C9="",D9=""),"",D9-C9) | F9: No
A10: Temporary lodging | E10: =IF(AND(C10="",D10=""),"",D10-C10) | F10: No
A11: Utilities / setup | E11: =IF(AND(C11="",D11=""),"",D11-C11) | F11: No
A12: Packing supplies | E12: =IF(AND(C12="",D12=""),"",D12-C12) | F12: No
A13: Meals during move | E13: =IF(AND(C13="",D13=""),"",D13-C13) | F13: No
A14: Cleaning / repairs | E14: =IF(AND(C14="",D14=""),"",D14-C14) | F14: No
A15: Unexpected costs | E15: =IF(AND(C15="",D15=""),"",D15-C15) | F15: No
A16: Other | E16: =IF(AND(C16="",D16=""),"",D16-C16) | F16: No
A18: TOTAL | C18: =SUM(C5:C17) -> 0 | D18: =SUM(D5:D17) -> 0 | E18: =SUM(E5:E17) -> 0

Sheet Contingencies
A1: CHANGE & CONTINGENCY LOG
A2: When plans change, record the impact, the next action, and who owns it.
A4: Date Identified | B4: What Changed? | C4: Affected Booking / Task | D4: Impact | E4: Next Action | F4: Responsible Person / Company | G4: Resolved?
